aind_data_transfer_lite/__init__.py
aind_data_transfer_lite/models.py
aind_data_transfer_lite/ui.py
aind_data_transfer_lite/upload_data.py
aind_data_transfer_lite-0.4.3.dist-info/licenses/LICENSE
aind_data_transfer_lite-0.4.3.dist-info/METADATA
aind_data_transfer_lite-0.4.3.dist-info/WHEEL
aind_data_transfer_lite-0.4.3.dist-info/top_level.txt
aind_data_transfer_lite-0.4.3.dist-info/RECORD
