Metadata-Version: 2.4
Name: aind-data-transfer-lite
Version: 0.4.3
Summary: Generated from aind-library-template
Author: Allen Institute for Neural Dynamics
License: MIT
Classifier: Programming Language :: Python :: 3
Requires-Python: >=3.10
License-File: LICENSE
Requires-Dist: aind-data-access-api
Requires-Dist: aind-data-schema-models<5.0
Requires-Dist: awscli
Requires-Dist: boto3
Requires-Dist: magic-class>=0.7.0
Requires-Dist: magicgui==0.10.1
Requires-Dist: pydantic<2.12,>=2.0
Requires-Dist: pydantic-settings<3.0,>=2.8.0
Requires-Dist: PyQt5>=5.15.11
Provides-Extra: dev
Requires-Dist: black; extra == "dev"
Requires-Dist: coverage; extra == "dev"
Requires-Dist: flake8; extra == "dev"
Requires-Dist: interrogate; extra == "dev"
Requires-Dist: isort; extra == "dev"
Requires-Dist: Sphinx; extra == "dev"
Requires-Dist: furo; extra == "dev"
Dynamic: license-file
